{
  "symbol": "O:SPXW250313P05510000",
  "underlying_symbol": "^SPX",
  "expiry": "2025-03-13T00:00:00",
  "strike": 5510.0,
  "contract_type": "put",
  "data": [
    {
      "open": 4.5,
      "high": 5.9,
      "low": 4.5,
      "close": 5.5,
      "volume": 117,
      "vwap": 5.1869,
      "timestamp": "2025-03-13T13:30:00+00:00"
    },
    {
      "open": 5.5,
      "high": 5.55,
      "low": 4.62,
      "close": 5,
      "volume": 61,
      "vwap": 4.9226,
      "timestamp": "2025-03-13T13:31:00+00:00"
    },
    {
      "open": 4.9,
      "high": 4.9,
      "low": 4.4,
      "close": 4.8,
      "volume": 43,
      "vwap": 4.6481,
      "timestamp": "2025-03-13T13:32:00+00:00"
    },
    {
      "open": 4.8,
      "high": 5.85,
      "low": 4.74,
      "close": 5.45,
      "volume": 66,
      "vwap": 5.4073,
      "timestamp": "2025-03-13T13:33:00+00:00"
    },
    {
      "open": 5.69,
      "high": 5.9,
      "low": 4.4,
      "close": 4.48,
      "volume": 41,
      "vwap": 5.18,
      "timestamp": "2025-03-13T13:34:00+00:00"
    },
    {
      "open": 4.5,
      "high": 5,
      "low": 4.25,
      "close": 4.5,
      "volume": 122,
      "vwap": 4.6103,
      "timestamp": "2025-03-13T13:35:00+00:00"
    },
    {
      "open": 4.56,
      "high": 5.9,
      "low": 4,
      "close": 5.9,
      "volume": 113,
      "vwap": 5.0787,
      "timestamp": "2025-03-13T13:36:00+00:00"
    },
    {
      "open": 5.8,
      "high": 5.8,
      "low": 4.4,
      "close": 4.8,
      "volume": 112,
      "vwap": 5.1189,
      "timestamp": "2025-03-13T13:37:00+00:00"
    },
    {
      "open": 4.61,
      "high": 4.68,
      "low": 4.2,
      "close": 4.2,
      "volume": 48,
      "vwap": 4.4817,
      "timestamp": "2025-03-13T13:38:00+00:00"
    },
    {
      "open": 4.2,
      "high": 4.9,
      "low": 4.2,
      "close": 4.6,
      "volume": 40,
      "vwap": 4.6288,
      "timestamp": "2025-03-13T13:39:00+00:00"
    },
    {
      "open": 4.3,
      "high": 4.65,
      "low": 3.9,
      "close": 4.62,
      "volume": 139,
      "vwap": 4.4843,
      "timestamp": "2025-03-13T13:40:00+00:00"
    },
    {
      "open": 4.73,
      "high": 4.8,
      "low": 4.1,
      "close": 4.5,
      "volume": 33,
      "vwap": 4.6655,
      "timestamp": "2025-03-13T13:41:00+00:00"
    },
    {
      "open": 4.3,
      "high": 4.3,
      "low": 3.53,
      "close": 4.07,
      "volume": 76,
      "vwap": 3.7921,
      "timestamp": "2025-03-13T13:42:00+00:00"
    },
    {
      "open": 4.3,
      "high": 5.5,
      "low": 4.3,
      "close": 4.64,
      "volume": 77,
      "vwap": 4.9109,
      "timestamp": "2025-03-13T13:43:00+00:00"
    },
    {
      "open": 4.7,
      "high": 5.67,
      "low": 4.7,
      "close": 5.5,
      "volume": 51,
      "vwap": 5.2145,
      "timestamp": "2025-03-13T13:44:00+00:00"
    },
    {
      "open": 5.6,
      "high": 6.23,
      "low": 4.98,
      "close": 5,
      "volume": 104,
      "vwap": 5.7338,
      "timestamp": "2025-03-13T13:45:00+00:00"
    },
    {
      "open": 5,
      "high": 5.6,
      "low": 4.8,
      "close": 5.53,
      "volume": 42,
      "vwap": 5.3479,
      "timestamp": "2025-03-13T13:46:00+00:00"
    },
    {
      "open": 5.72,
      "high": 5.8,
      "low": 5,
      "close": 5,
      "volume": 37,
      "vwap": 5.4292,
      "timestamp": "2025-03-13T13:47:00+00:00"
    },
    {
      "open": 5.2,
      "high": 5.8,
      "low": 5.2,
      "close": 5.4,
      "volume": 37,
      "vwap": 5.5881,
      "timestamp": "2025-03-13T13:48:00+00:00"
    },
    {
      "open": 5.62,
      "high": 5.86,
      "low": 5.39,
      "close": 5.7,
      "volume": 33,
      "vwap": 5.6824,
      "timestamp": "2025-03-13T13:49:00+00:00"
    },
    {
      "open": 5.9,
      "high": 7.04,
      "low": 5.3,
      "close": 6.7,
      "volume": 144,
      "vwap": 6.3534,
      "timestamp": "2025-03-13T13:50:00+00:00"
    },
    {
      "open": 6.8,
      "high": 6.8,
      "low": 5.9,
      "close": 6.05,
      "volume": 135,
      "vwap": 6.4907,
      "timestamp": "2025-03-13T13:51:00+00:00"
    },
    {
      "open": 6,
      "high": 6.6,
      "low": 6,
      "close": 6.4,
      "volume": 49,
      "vwap": 6.4269,
      "timestamp": "2025-03-13T13:52:00+00:00"
    },
    {
      "open": 6.6,
      "high": 7,
      "low": 6.6,
      "close": 6.7,
      "volume": 28,
      "vwap": 6.8079,
      "timestamp": "2025-03-13T13:53:00+00:00"
    },
    {
      "open": 6.6,
      "high": 8.1,
      "low": 6.5,
      "close": 7.2,
      "volume": 282,
      "vwap": 7.5399,
      "timestamp": "2025-03-13T13:54:00+00:00"
    },
    {
      "open": 7.2,
      "high": 8,
      "low": 6.83,
      "close": 7.2,
      "volume": 114,
      "vwap": 7.3384,
      "timestamp": "2025-03-13T13:55:00+00:00"
    },
    {
      "open": 7.2,
      "high": 9,
      "low": 7,
      "close": 8.7,
      "volume": 160,
      "vwap": 7.9013,
      "timestamp": "2025-03-13T13:56:00+00:00"
    },
    {
      "open": 8.7,
      "high": 9.5,
      "low": 8.2,
      "close": 8.5,
      "volume": 138,
      "vwap": 8.8982,
      "timestamp": "2025-03-13T13:57:00+00:00"
    },
    {
      "open": 8.4,
      "high": 9.1,
      "low": 7.8,
      "close": 7.8,
      "volume": 72,
      "vwap": 8.8676,
      "timestamp": "2025-03-13T13:58:00+00:00"
    },
    {
      "open": 7.8,
      "high": 8.17,
      "low": 7.58,
      "close": 8,
      "volume": 59,
      "vwap": 7.8349,
      "timestamp": "2025-03-13T13:59:00+00:00"
    },
    {
      "open": 8.4,
      "high": 9.5,
      "low": 7.7,
      "close": 7.7,
      "volume": 137,
      "vwap": 8.8155,
      "timestamp": "2025-03-13T14:00:00+00:00"
    },
    {
      "open": 8.26,
      "high": 8.8,
      "low": 8.11,
      "close": 8.3,
      "volume": 73,
      "vwap": 8.3433,
      "timestamp": "2025-03-13T14:01:00+00:00"
    },
    {
      "open": 8.36,
      "high": 8.9,
      "low": 8,
      "close": 8.1,
      "volume": 90,
      "vwap": 8.4116,
      "timestamp": "2025-03-13T14:02:00+00:00"
    },
    {
      "open": 8.2,
      "high": 8.2,
      "low": 6.2,
      "close": 6.8,
      "volume": 92,
      "vwap": 6.6164,
      "timestamp": "2025-03-13T14:03:00+00:00"
    },
    {
      "open": 7,
      "high": 7.77,
      "low": 6.9,
      "close": 6.9,
      "volume": 70,
      "vwap": 7.4193,
      "timestamp": "2025-03-13T14:04:00+00:00"
    },
    {
      "open": 6.8,
      "high": 6.8,
      "low": 5.4,
      "close": 5.98,
      "volume": 171,
      "vwap": 5.7472,
      "timestamp": "2025-03-13T14:05:00+00:00"
    },
    {
      "open": 5.6,
      "high": 6.3,
      "low": 5.6,
      "close": 5.7,
      "volume": 45,
      "vwap": 5.9504,
      "timestamp": "2025-03-13T14:06:00+00:00"
    },
    {
      "open": 6,
      "high": 6.25,
      "low": 5.4,
      "close": 5.52,
      "volume": 75,
      "vwap": 5.6984,
      "timestamp": "2025-03-13T14:07:00+00:00"
    },
    {
      "open": 5.53,
      "high": 6.1,
      "low": 5.24,
      "close": 5.5,
      "volume": 58,
      "vwap": 5.5922,
      "timestamp": "2025-03-13T14:08:00+00:00"
    },
    {
      "open": 5.56,
      "high": 5.56,
      "low": 5.1,
      "close": 5.4,
      "volume": 37,
      "vwap": 5.2608,
      "timestamp": "2025-03-13T14:09:00+00:00"
    },
    {
      "open": 5.4,
      "high": 5.75,
      "low": 5.2,
      "close": 5.4,
      "volume": 54,
      "vwap": 5.4869,
      "timestamp": "2025-03-13T14:10:00+00:00"
    },
    {
      "open": 5.7,
      "high": 6.32,
      "low": 5.2,
      "close": 5.9,
      "volume": 93,
      "vwap": 5.9206,
      "timestamp": "2025-03-13T14:11:00+00:00"
    },
    {
      "open": 5.9,
      "high": 5.9,
      "low": 4.35,
      "close": 4.35,
      "volume": 91,
      "vwap": 4.7827,
      "timestamp": "2025-03-13T14:12:00+00:00"
    },
    {
      "open": 4.33,
      "high": 4.71,
      "low": 4.27,
      "close": 4.71,
      "volume": 33,
      "vwap": 4.4288,
      "timestamp": "2025-03-13T14:13:00+00:00"
    },
    {
      "open": 4.9,
      "high": 4.9,
      "low": 3.8,
      "close": 3.8,
      "volume": 131,
      "vwap": 4.2309,
      "timestamp": "2025-03-13T14:14:00+00:00"
    },
    {
      "open": 3.8,
      "high": 4.2,
      "low": 3.5,
      "close": 3.8,
      "volume": 105,
      "vwap": 3.8138,
      "timestamp": "2025-03-13T14:15:00+00:00"
    },
    {
      "open": 3.8,
      "high": 4.1,
      "low": 3.74,
      "close": 3.9,
      "volume": 82,
      "vwap": 3.8491,
      "timestamp": "2025-03-13T14:16:00+00:00"
    },
    {
      "open": 3.86,
      "high": 3.86,
      "low": 3.4,
      "close": 3.6,
      "volume": 51,
      "vwap": 3.5253,
      "timestamp": "2025-03-13T14:17:00+00:00"
    },
    {
      "open": 3.57,
      "high": 3.85,
      "low": 3.34,
      "close": 3.34,
      "volume": 44,
      "vwap": 3.5827,
      "timestamp": "2025-03-13T14:18:00+00:00"
    },
    {
      "open": 3.4,
      "high": 3.4,
      "low": 2.8,
      "close": 2.95,
      "volume": 182,
      "vwap": 2.959,
      "timestamp": "2025-03-13T14:19:00+00:00"
    },
    {
      "open": 3,
      "high": 3.01,
      "low": 2.77,
      "close": 2.9,
      "volume": 77,
      "vwap": 2.9178,
      "timestamp": "2025-03-13T14:20:00+00:00"
    },
    {
      "open": 2.9,
      "high": 3.6,
      "low": 2.8,
      "close": 3.3,
      "volume": 404,
      "vwap": 3.1062,
      "timestamp": "2025-03-13T14:21:00+00:00"
    },
    {
      "open": 3.4,
      "high": 3.6,
      "low": 3.3,
      "close": 3.35,
      "volume": 33,
      "vwap": 3.4433,
      "timestamp": "2025-03-13T14:22:00+00:00"
    },
    {
      "open": 3.5,
      "high": 3.7,
      "low": 3.35,
      "close": 3.5,
      "volume": 51,
      "vwap": 3.532,
      "timestamp": "2025-03-13T14:23:00+00:00"
    },
    {
      "open": 3.4,
      "high": 3.66,
      "low": 2.85,
      "close": 2.85,
      "volume": 224,
      "vwap": 3.0492,
      "timestamp": "2025-03-13T14:24:00+00:00"
    },
    {
      "open": 2.85,
      "high": 2.95,
      "low": 2.35,
      "close": 2.7,
      "volume": 233,
      "vwap": 2.4581,
      "timestamp": "2025-03-13T14:25:00+00:00"
    },
    {
      "open": 2.67,
      "high": 2.7,
      "low": 2.5,
      "close": 2.7,
      "volume": 33,
      "vwap": 2.6667,
      "timestamp": "2025-03-13T14:26:00+00:00"
    },
    {
      "open": 2.85,
      "high": 3.1,
      "low": 2.7,
      "close": 2.95,
      "volume": 72,
      "vwap": 2.9058,
      "timestamp": "2025-03-13T14:27:00+00:00"
    },
    {
      "open": 2.85,
      "high": 3.5,
      "low": 2.85,
      "close": 3.5,
      "volume": 99,
      "vwap": 3.1084,
      "timestamp": "2025-03-13T14:28:00+00:00"
    },
    {
      "open": 3.8,
      "high": 4.2,
      "low": 3.6,
      "close": 3.9,
      "volume": 152,
      "vwap": 3.7928,
      "timestamp": "2025-03-13T14:29:00+00:00"
    },
    {
      "open": 3.9,
      "high": 3.9,
      "low": 2.8,
      "close": 3,
      "volume": 50,
      "vwap": 3.2576,
      "timestamp": "2025-03-13T14:30:00+00:00"
    },
    {
      "open": 3.03,
      "high": 3.25,
      "low": 2.7,
      "close": 3.25,
      "volume": 48,
      "vwap": 2.9077,
      "timestamp": "2025-03-13T14:31:00+00:00"
    },
    {
      "open": 3.3,
      "high": 3.3,
      "low": 3.1,
      "close": 3.2,
      "volume": 19,
      "vwap": 3.2579,
      "timestamp": "2025-03-13T14:32:00+00:00"
    },
    {
      "open": 3.1,
      "high": 3.8,
      "low": 3.1,
      "close": 3.7,
      "volume": 73,
      "vwap": 3.4018,
      "timestamp": "2025-03-13T14:33:00+00:00"
    },
    {
      "open": 3.72,
      "high": 4.06,
      "low": 3.5,
      "close": 3.7,
      "volume": 108,
      "vwap": 3.7895,
      "timestamp": "2025-03-13T14:34:00+00:00"
    },
    {
      "open": 3.6,
      "high": 4.4,
      "low": 3.5,
      "close": 3.8,
      "volume": 34,
      "vwap": 4.0044,
      "timestamp": "2025-03-13T14:35:00+00:00"
    },
    {
      "open": 4.1,
      "high": 4.84,
      "low": 4.1,
      "close": 4.7,
      "volume": 148,
      "vwap": 4.3804,
      "timestamp": "2025-03-13T14:36:00+00:00"
    },
    {
      "open": 4.8,
      "high": 4.8,
      "low": 4.16,
      "close": 4.4,
      "volume": 61,
      "vwap": 4.4652,
      "timestamp": "2025-03-13T14:37:00+00:00"
    },
    {
      "open": 4.4,
      "high": 4.7,
      "low": 4.3,
      "close": 4.4,
      "volume": 30,
      "vwap": 4.4587,
      "timestamp": "2025-03-13T14:38:00+00:00"
    },
    {
      "open": 4.5,
      "high": 5,
      "low": 4.3,
      "close": 4.3,
      "volume": 55,
      "vwap": 4.6787,
      "timestamp": "2025-03-13T14:39:00+00:00"
    },
    {
      "open": 4.3,
      "high": 4.8,
      "low": 4.2,
      "close": 4.6,
      "volume": 31,
      "vwap": 4.5242,
      "timestamp": "2025-03-13T14:40:00+00:00"
    },
    {
      "open": 4.5,
      "high": 4.8,
      "low": 4.5,
      "close": 4.8,
      "volume": 24,
      "vwap": 4.7542,
      "timestamp": "2025-03-13T14:41:00+00:00"
    },
    {
      "open": 4.7,
      "high": 5.3,
      "low": 4.6,
      "close": 5.1,
      "volume": 59,
      "vwap": 5.0158,
      "timestamp": "2025-03-13T14:42:00+00:00"
    },
    {
      "open": 5,
      "high": 5,
      "low": 4.35,
      "close": 4.51,
      "volume": 139,
      "vwap": 4.5563,
      "timestamp": "2025-03-13T14:43:00+00:00"
    },
    {
      "open": 4.61,
      "high": 4.82,
      "low": 4.25,
      "close": 4.4,
      "volume": 126,
      "vwap": 4.4071,
      "timestamp": "2025-03-13T14:44:00+00:00"
    },
    {
      "open": 4.5,
      "high": 4.65,
      "low": 3.9,
      "close": 4.1,
      "volume": 70,
      "vwap": 4.21,
      "timestamp": "2025-03-13T14:45:00+00:00"
    },
    {
      "open": 4,
      "high": 4.4,
      "low": 3.8,
      "close": 4.4,
      "volume": 81,
      "vwap": 4.0298,
      "timestamp": "2025-03-13T14:46:00+00:00"
    },
    {
      "open": 4.9,
      "high": 4.9,
      "low": 4.2,
      "close": 4.67,
      "volume": 27,
      "vwap": 4.6911,
      "timestamp": "2025-03-13T14:47:00+00:00"
    },
    {
      "open": 4.7,
      "high": 5.1,
      "low": 4.7,
      "close": 4.79,
      "volume": 125,
      "vwap": 4.847,
      "timestamp": "2025-03-13T14:48:00+00:00"
    },
    {
      "open": 5.2,
      "high": 5.2,
      "low": 4.6,
      "close": 4.6,
      "volume": 42,
      "vwap": 5.0238,
      "timestamp": "2025-03-13T14:49:00+00:00"
    },
    {
      "open": 4.6,
      "high": 4.6,
      "low": 3.98,
      "close": 4,
      "volume": 82,
      "vwap": 4.3157,
      "timestamp": "2025-03-13T14:50:00+00:00"
    },
    {
      "open": 4.2,
      "high": 4.2,
      "low": 3.4,
      "close": 3.57,
      "volume": 75,
      "vwap": 3.7689,
      "timestamp": "2025-03-13T14:51:00+00:00"
    },
    {
      "open": 3.7,
      "high": 3.8,
      "low": 3.4,
      "close": 3.76,
      "volume": 43,
      "vwap": 3.5707,
      "timestamp": "2025-03-13T14:52:00+00:00"
    },
    {
      "open": 3.77,
      "high": 3.8,
      "low": 3.1,
      "close": 3.11,
      "volume": 95,
      "vwap": 3.2828,
      "timestamp": "2025-03-13T14:53:00+00:00"
    },
    {
      "open": 3.12,
      "high": 3.9,
      "low": 3.1,
      "close": 3.7,
      "volume": 49,
      "vwap": 3.5206,
      "timestamp": "2025-03-13T14:54:00+00:00"
    },
    {
      "open": 3.7,
      "high": 4.1,
      "low": 3.7,
      "close": 3.7,
      "volume": 56,
      "vwap": 3.8954,
      "timestamp": "2025-03-13T14:55:00+00:00"
    },
    {
      "open": 3.9,
      "high": 4.5,
      "low": 3.8,
      "close": 4.4,
      "volume": 75,
      "vwap": 4.2173,
      "timestamp": "2025-03-13T14:56:00+00:00"
    },
    {
      "open": 4.5,
      "high": 4.8,
      "low": 4.5,
      "close": 4.6,
      "volume": 78,
      "vwap": 4.6749,
      "timestamp": "2025-03-13T14:57:00+00:00"
    },
    {
      "open": 4.7,
      "high": 5.11,
      "low": 4.7,
      "close": 4.7,
      "volume": 82,
      "vwap": 4.8528,
      "timestamp": "2025-03-13T14:58:00+00:00"
    },
    {
      "open": 4.7,
      "high": 4.9,
      "low": 4.5,
      "close": 4.6,
      "volume": 39,
      "vwap": 4.7597,
      "timestamp": "2025-03-13T14:59:00+00:00"
    },
    {
      "open": 4.23,
      "high": 4.23,
      "low": 3.4,
      "close": 3.9,
      "volume": 18,
      "vwap": 3.7106,
      "timestamp": "2025-03-13T15:00:00+00:00"
    },
    {
      "open": 3.6,
      "high": 3.8,
      "low": 3.4,
      "close": 3.7,
      "volume": 18,
      "vwap": 3.62,
      "timestamp": "2025-03-13T15:01:00+00:00"
    },
    {
      "open": 3.7,
      "high": 3.7,
      "low": 3.46,
      "close": 3.55,
      "volume": 18,
      "vwap": 3.5372,
      "timestamp": "2025-03-13T15:02:00+00:00"
    },
    {
      "open": 3.5,
      "high": 3.7,
      "low": 3.3,
      "close": 3.4,
      "volume": 27,
      "vwap": 3.4611,
      "timestamp": "2025-03-13T15:03:00+00:00"
    },
    {
      "open": 3.5,
      "high": 3.6,
      "low": 3.5,
      "close": 3.6,
      "volume": 20,
      "vwap": 3.565,
      "timestamp": "2025-03-13T15:04:00+00:00"
    },
    {
      "open": 3.7,
      "high": 3.7,
      "low": 3.2,
      "close": 3.67,
      "volume": 42,
      "vwap": 3.4971,
      "timestamp": "2025-03-13T15:05:00+00:00"
    },
    {
      "open": 3.77,
      "high": 4.2,
      "low": 3.6,
      "close": 4.07,
      "volume": 73,
      "vwap": 4.0107,
      "timestamp": "2025-03-13T15:06:00+00:00"
    },
    {
      "open": 4.2,
      "high": 5,
      "low": 4.2,
      "close": 5,
      "volume": 69,
      "vwap": 4.5716,
      "timestamp": "2025-03-13T15:07:00+00:00"
    },
    {
      "open": 5,
      "high": 5.6,
      "low": 4.7,
      "close": 5.6,
      "volume": 200,
      "vwap": 5.332,
      "timestamp": "2025-03-13T15:08:00+00:00"
    },
    {
      "open": 5.4,
      "high": 5.8,
      "low": 5.3,
      "close": 5.3,
      "volume": 119,
      "vwap": 5.5484,
      "timestamp": "2025-03-13T15:09:00+00:00"
    },
    {
      "open": 5.2,
      "high": 5.2,
      "low": 4.6,
      "close": 4.9,
      "volume": 68,
      "vwap": 4.8904,
      "timestamp": "2025-03-13T15:10:00+00:00"
    },
    {
      "open": 4.91,
      "high": 5.2,
      "low": 4.8,
      "close": 5.2,
      "volume": 83,
      "vwap": 4.9775,
      "timestamp": "2025-03-13T15:11:00+00:00"
    },
    {
      "open": 5.4,
      "high": 6.1,
      "low": 5.2,
      "close": 5.2,
      "volume": 65,
      "vwap": 5.7351,
      "timestamp": "2025-03-13T15:12:00+00:00"
    },
    {
      "open": 5.5,
      "high": 5.7,
      "low": 5.1,
      "close": 5.4,
      "volume": 29,
      "vwap": 5.4024,
      "timestamp": "2025-03-13T15:13:00+00:00"
    },
    {
      "open": 5.3,
      "high": 5.6,
      "low": 5.3,
      "close": 5.6,
      "volume": 9,
      "vwap": 5.5167,
      "timestamp": "2025-03-13T15:14:00+00:00"
    },
    {
      "open": 5.2,
      "high": 5.7,
      "low": 5.2,
      "close": 5.6,
      "volume": 100,
      "vwap": 5.4541,
      "timestamp": "2025-03-13T15:15:00+00:00"
    },
    {
      "open": 5.7,
      "high": 6.02,
      "low": 5.1,
      "close": 5.4,
      "volume": 69,
      "vwap": 5.6375,
      "timestamp": "2025-03-13T15:16:00+00:00"
    },
    {
      "open": 5.2,
      "high": 5.5,
      "low": 5,
      "close": 5.2,
      "volume": 19,
      "vwap": 5.3184,
      "timestamp": "2025-03-13T15:17:00+00:00"
    },
    {
      "open": 5.2,
      "high": 5.6,
      "low": 5.1,
      "close": 5.1,
      "volume": 7,
      "vwap": 5.3457,
      "timestamp": "2025-03-13T15:18:00+00:00"
    },
    {
      "open": 5.4,
      "high": 5.4,
      "low": 4.8,
      "close": 4.9,
      "volume": 55,
      "vwap": 5.0936,
      "timestamp": "2025-03-13T15:19:00+00:00"
    },
    {
      "open": 5.1,
      "high": 5.5,
      "low": 5,
      "close": 5.2,
      "volume": 95,
      "vwap": 5.2148,
      "timestamp": "2025-03-13T15:20:00+00:00"
    },
    {
      "open": 5.3,
      "high": 5.87,
      "low": 5.3,
      "close": 5.87,
      "volume": 64,
      "vwap": 5.6028,
      "timestamp": "2025-03-13T15:21:00+00:00"
    },
    {
      "open": 5.52,
      "high": 6.05,
      "low": 5.52,
      "close": 5.8,
      "volume": 84,
      "vwap": 5.8982,
      "timestamp": "2025-03-13T15:22:00+00:00"
    },
    {
      "open": 6,
      "high": 6.12,
      "low": 5.5,
      "close": 5.6,
      "volume": 77,
      "vwap": 5.8155,
      "timestamp": "2025-03-13T15:23:00+00:00"
    },
    {
      "open": 5.5,
      "high": 5.6,
      "low": 5.2,
      "close": 5.35,
      "volume": 31,
      "vwap": 5.4719,
      "timestamp": "2025-03-13T15:24:00+00:00"
    },
    {
      "open": 5.1,
      "high": 6.3,
      "low": 4.8,
      "close": 6.3,
      "volume": 145,
      "vwap": 5.2867,
      "timestamp": "2025-03-13T15:25:00+00:00"
    },
    {
      "open": 6.2,
      "high": 6.9,
      "low": 5.9,
      "close": 6.4,
      "volume": 152,
      "vwap": 6.3374,
      "timestamp": "2025-03-13T15:26:00+00:00"
    },
    {
      "open": 6.5,
      "high": 7.35,
      "low": 6.5,
      "close": 7.06,
      "volume": 170,
      "vwap": 7.0889,
      "timestamp": "2025-03-13T15:27:00+00:00"
    },
    {
      "open": 7,
      "high": 7,
      "low": 5.9,
      "close": 6.1,
      "volume": 80,
      "vwap": 6.5091,
      "timestamp": "2025-03-13T15:28:00+00:00"
    },
    {
      "open": 6.06,
      "high": 6.9,
      "low": 6.06,
      "close": 6.5,
      "volume": 49,
      "vwap": 6.4298,
      "timestamp": "2025-03-13T15:29:00+00:00"
    },
    {
      "open": 6.7,
      "high": 6.7,
      "low": 6.2,
      "close": 6.6,
      "volume": 16,
      "vwap": 6.5406,
      "timestamp": "2025-03-13T15:30:00+00:00"
    },
    {
      "open": 6.8,
      "high": 7.1,
      "low": 6.5,
      "close": 7,
      "volume": 67,
      "vwap": 6.6955,
      "timestamp": "2025-03-13T15:31:00+00:00"
    },
    {
      "open": 7,
      "high": 7,
      "low": 6,
      "close": 6.1,
      "volume": 115,
      "vwap": 6.5083,
      "timestamp": "2025-03-13T15:32:00+00:00"
    },
    {
      "open": 6,
      "high": 6,
      "low": 5.7,
      "close": 5.9,
      "volume": 102,
      "vwap": 5.961,
      "timestamp": "2025-03-13T15:33:00+00:00"
    },
    {
      "open": 6.1,
      "high": 6.6,
      "low": 6.1,
      "close": 6.35,
      "volume": 30,
      "vwap": 6.4003,
      "timestamp": "2025-03-13T15:34:00+00:00"
    },
    {
      "open": 6.5,
      "high": 7.9,
      "low": 6.5,
      "close": 7.5,
      "volume": 120,
      "vwap": 7.2835,
      "timestamp": "2025-03-13T15:35:00+00:00"
    },
    {
      "open": 7.7,
      "high": 9.72,
      "low": 7.7,
      "close": 9.2,
      "volume": 253,
      "vwap": 9.0164,
      "timestamp": "2025-03-13T15:36:00+00:00"
    },
    {
      "open": 9.2,
      "high": 9.2,
      "low": 8.3,
      "close": 8.9,
      "volume": 69,
      "vwap": 8.8077,
      "timestamp": "2025-03-13T15:37:00+00:00"
    },
    {
      "open": 9.1,
      "high": 10.5,
      "low": 9.1,
      "close": 9.6,
      "volume": 178,
      "vwap": 9.9013,
      "timestamp": "2025-03-13T15:38:00+00:00"
    },
    {
      "open": 9.75,
      "high": 9.8,
      "low": 8.9,
      "close": 9.3,
      "volume": 119,
      "vwap": 9.3004,
      "timestamp": "2025-03-13T15:39:00+00:00"
    },
    {
      "open": 9,
      "high": 10.61,
      "low": 9,
      "close": 10.4,
      "volume": 114,
      "vwap": 10.0385,
      "timestamp": "2025-03-13T15:40:00+00:00"
    },
    {
      "open": 10.4,
      "high": 10.77,
      "low": 9.8,
      "close": 9.9,
      "volume": 195,
      "vwap": 10.384,
      "timestamp": "2025-03-13T15:41:00+00:00"
    },
    {
      "open": 10.1,
      "high": 10.2,
      "low": 7,
      "close": 8.4,
      "volume": 140,
      "vwap": 9.3121,
      "timestamp": "2025-03-13T15:42:00+00:00"
    },
    {
      "open": 8.5,
      "high": 8.7,
      "low": 6.3,
      "close": 6.9,
      "volume": 192,
      "vwap": 6.7298,
      "timestamp": "2025-03-13T15:43:00+00:00"
    },
    {
      "open": 6.5,
      "high": 7,
      "low": 4.6,
      "close": 6.7,
      "volume": 318,
      "vwap": 6.141,
      "timestamp": "2025-03-13T15:44:00+00:00"
    },
    {
      "open": 7,
      "high": 7.5,
      "low": 6.54,
      "close": 7.2,
      "volume": 112,
      "vwap": 7.1327,
      "timestamp": "2025-03-13T15:45:00+00:00"
    },
    {
      "open": 7.2,
      "high": 8.8,
      "low": 7.2,
      "close": 8.2,
      "volume": 171,
      "vwap": 7.6731,
      "timestamp": "2025-03-13T15:46:00+00:00"
    },
    {
      "open": 8.6,
      "high": 8.6,
      "low": 7.4,
      "close": 7.5,
      "volume": 99,
      "vwap": 7.9741,
      "timestamp": "2025-03-13T15:47:00+00:00"
    },
    {
      "open": 7.4,
      "high": 8,
      "low": 7.4,
      "close": 7.8,
      "volume": 76,
      "vwap": 7.7904,
      "timestamp": "2025-03-13T15:48:00+00:00"
    },
    {
      "open": 7.6,
      "high": 7.6,
      "low": 6.4,
      "close": 6.68,
      "volume": 50,
      "vwap": 6.8346,
      "timestamp": "2025-03-13T15:49:00+00:00"
    },
    {
      "open": 7.3,
      "high": 8,
      "low": 7.3,
      "close": 8,
      "volume": 66,
      "vwap": 7.7188,
      "timestamp": "2025-03-13T15:50:00+00:00"
    },
    {
      "open": 8.3,
      "high": 9.5,
      "low": 8.3,
      "close": 8.7,
      "volume": 140,
      "vwap": 8.8691,
      "timestamp": "2025-03-13T15:51:00+00:00"
    },
    {
      "open": 8.87,
      "high": 9.8,
      "low": 8.3,
      "close": 8.3,
      "volume": 87,
      "vwap": 8.9769,
      "timestamp": "2025-03-13T15:52:00+00:00"
    },
    {
      "open": 8.4,
      "high": 9.3,
      "low": 8.3,
      "close": 9.1,
      "volume": 48,
      "vwap": 8.8573,
      "timestamp": "2025-03-13T15:53:00+00:00"
    },
    {
      "open": 9.07,
      "high": 9.66,
      "low": 8.9,
      "close": 9.5,
      "volume": 88,
      "vwap": 9.2966,
      "timestamp": "2025-03-13T15:54:00+00:00"
    },
    {
      "open": 9,
      "high": 10,
      "low": 9,
      "close": 9.5,
      "volume": 42,
      "vwap": 9.7174,
      "timestamp": "2025-03-13T15:55:00+00:00"
    },
    {
      "open": 9.9,
      "high": 11.2,
      "low": 9.9,
      "close": 10.4,
      "volume": 155,
      "vwap": 10.8437,
      "timestamp": "2025-03-13T15:56:00+00:00"
    },
    {
      "open": 10.7,
      "high": 11.15,
      "low": 9.3,
      "close": 9.5,
      "volume": 140,
      "vwap": 10.3586,
      "timestamp": "2025-03-13T15:57:00+00:00"
    },
    {
      "open": 9.6,
      "high": 10.1,
      "low": 9.3,
      "close": 9.9,
      "volume": 91,
      "vwap": 9.723,
      "timestamp": "2025-03-13T15:58:00+00:00"
    },
    {
      "open": 9.96,
      "high": 11.07,
      "low": 9.96,
      "close": 10.69,
      "volume": 51,
      "vwap": 10.5033,
      "timestamp": "2025-03-13T15:59:00+00:00"
    },
    {
      "open": 10.8,
      "high": 11.5,
      "low": 10.1,
      "close": 10.72,
      "volume": 114,
      "vwap": 10.8021,
      "timestamp": "2025-03-13T16:00:00+00:00"
    },
    {
      "open": 10.44,
      "high": 11.2,
      "low": 10.22,
      "close": 10.7,
      "volume": 65,
      "vwap": 10.802,
      "timestamp": "2025-03-13T16:01:00+00:00"
    },
    {
      "open": 10.6,
      "high": 11,
      "low": 9.6,
      "close": 9.8,
      "volume": 80,
      "vwap": 9.995,
      "timestamp": "2025-03-13T16:02:00+00:00"
    },
    {
      "open": 9.81,
      "high": 10.2,
      "low": 9.3,
      "close": 9.3,
      "volume": 51,
      "vwap": 9.7667,
      "timestamp": "2025-03-13T16:03:00+00:00"
    },
    {
      "open": 9.2,
      "high": 9.2,
      "low": 8,
      "close": 8.2,
      "volume": 80,
      "vwap": 8.5439,
      "timestamp": "2025-03-13T16:04:00+00:00"
    },
    {
      "open": 8.07,
      "high": 9.5,
      "low": 8,
      "close": 9.5,
      "volume": 120,
      "vwap": 8.7378,
      "timestamp": "2025-03-13T16:05:00+00:00"
    },
    {
      "open": 9.8,
      "high": 10.3,
      "low": 9.4,
      "close": 9.7,
      "volume": 62,
      "vwap": 9.8935,
      "timestamp": "2025-03-13T16:06:00+00:00"
    },
    {
      "open": 9.6,
      "high": 9.6,
      "low": 8.3,
      "close": 8.75,
      "volume": 62,
      "vwap": 8.696,
      "timestamp": "2025-03-13T16:07:00+00:00"
    },
    {
      "open": 8.5,
      "high": 8.5,
      "low": 7.3,
      "close": 7.4,
      "volume": 86,
      "vwap": 8.0516,
      "timestamp": "2025-03-13T16:08:00+00:00"
    },
    {
      "open": 6.8,
      "high": 7.7,
      "low": 6.8,
      "close": 7,
      "volume": 44,
      "vwap": 7.2875,
      "timestamp": "2025-03-13T16:09:00+00:00"
    },
    {
      "open": 6.9,
      "high": 7.9,
      "low": 6.9,
      "close": 7.9,
      "volume": 23,
      "vwap": 7.4652,
      "timestamp": "2025-03-13T16:10:00+00:00"
    },
    {
      "open": 8,
      "high": 9,
      "low": 8,
      "close": 8.1,
      "volume": 34,
      "vwap": 8.5338,
      "timestamp": "2025-03-13T16:11:00+00:00"
    },
    {
      "open": 8.1,
      "high": 8.2,
      "low": 7.2,
      "close": 7.9,
      "volume": 27,
      "vwap": 7.6759,
      "timestamp": "2025-03-13T16:12:00+00:00"
    },
    {
      "open": 7.8,
      "high": 8.2,
      "low": 7.8,
      "close": 8,
      "volume": 64,
      "vwap": 8.0844,
      "timestamp": "2025-03-13T16:13:00+00:00"
    },
    {
      "open": 7.98,
      "high": 9.3,
      "low": 7.98,
      "close": 9.1,
      "volume": 48,
      "vwap": 8.9131,
      "timestamp": "2025-03-13T16:14:00+00:00"
    },
    {
      "open": 9.27,
      "high": 10.2,
      "low": 9,
      "close": 9.99,
      "volume": 220,
      "vwap": 9.7165,
      "timestamp": "2025-03-13T16:15:00+00:00"
    },
    {
      "open": 10.2,
      "high": 10.6,
      "low": 9.2,
      "close": 9.2,
      "volume": 98,
      "vwap": 9.9373,
      "timestamp": "2025-03-13T16:16:00+00:00"
    },
    {
      "open": 9,
      "high": 10,
      "low": 8.9,
      "close": 9,
      "volume": 28,
      "vwap": 9.5429,
      "timestamp": "2025-03-13T16:17:00+00:00"
    },
    {
      "open": 9.75,
      "high": 9.75,
      "low": 8.5,
      "close": 8.5,
      "volume": 69,
      "vwap": 8.9142,
      "timestamp": "2025-03-13T16:18:00+00:00"
    },
    {
      "open": 8.65,
      "high": 9.27,
      "low": 8.3,
      "close": 8.6,
      "volume": 21,
      "vwap": 8.7605,
      "timestamp": "2025-03-13T16:19:00+00:00"
    },
    {
      "open": 8.8,
      "high": 9.1,
      "low": 8.1,
      "close": 8.6,
      "volume": 56,
      "vwap": 8.6625,
      "timestamp": "2025-03-13T16:20:00+00:00"
    },
    {
      "open": 8.19,
      "high": 9.32,
      "low": 8,
      "close": 9.32,
      "volume": 20,
      "vwap": 8.565,
      "timestamp": "2025-03-13T16:21:00+00:00"
    },
    {
      "open": 9.2,
      "high": 9.32,
      "low": 8.3,
      "close": 9.32,
      "volume": 30,
      "vwap": 8.812,
      "timestamp": "2025-03-13T16:22:00+00:00"
    },
    {
      "open": 9.7,
      "high": 9.7,
      "low": 9.31,
      "close": 9.44,
      "volume": 37,
      "vwap": 9.5619,
      "timestamp": "2025-03-13T16:23:00+00:00"
    },
    {
      "open": 9.6,
      "high": 9.8,
      "low": 9.1,
      "close": 9.7,
      "volume": 26,
      "vwap": 9.4469,
      "timestamp": "2025-03-13T16:24:00+00:00"
    },
    {
      "open": 9.8,
      "high": 9.8,
      "low": 9.4,
      "close": 9.6,
      "volume": 69,
      "vwap": 9.591,
      "timestamp": "2025-03-13T16:25:00+00:00"
    },
    {
      "open": 9.69,
      "high": 10.34,
      "low": 9.3,
      "close": 10.1,
      "volume": 33,
      "vwap": 9.9424,
      "timestamp": "2025-03-13T16:26:00+00:00"
    },
    {
      "open": 10.32,
      "high": 10.32,
      "low": 9.5,
      "close": 9.7,
      "volume": 35,
      "vwap": 9.8669,
      "timestamp": "2025-03-13T16:27:00+00:00"
    },
    {
      "open": 9.8,
      "high": 9.8,
      "low": 8.9,
      "close": 8.9,
      "volume": 16,
      "vwap": 9.5119,
      "timestamp": "2025-03-13T16:28:00+00:00"
    },
    {
      "open": 8.7,
      "high": 9.7,
      "low": 8.7,
      "close": 9.7,
      "volume": 17,
      "vwap": 9.2694,
      "timestamp": "2025-03-13T16:29:00+00:00"
    },
    {
      "open": 10,
      "high": 10.74,
      "low": 8.3,
      "close": 8.6,
      "volume": 65,
      "vwap": 9.2108,
      "timestamp": "2025-03-13T16:30:00+00:00"
    },
    {
      "open": 8.27,
      "high": 8.32,
      "low": 7.3,
      "close": 7.3,
      "volume": 78,
      "vwap": 7.7559,
      "timestamp": "2025-03-13T16:31:00+00:00"
    },
    {
      "open": 7.2,
      "high": 8.6,
      "low": 7.2,
      "close": 8,
      "volume": 46,
      "vwap": 8.0239,
      "timestamp": "2025-03-13T16:32:00+00:00"
    },
    {
      "open": 8.2,
      "high": 8.3,
      "low": 7.3,
      "close": 7.3,
      "volume": 41,
      "vwap": 7.7463,
      "timestamp": "2025-03-13T16:33:00+00:00"
    },
    {
      "open": 7.3,
      "high": 7.3,
      "low": 6.3,
      "close": 6.3,
      "volume": 151,
      "vwap": 6.6234,
      "timestamp": "2025-03-13T16:34:00+00:00"
    },
    {
      "open": 6.71,
      "high": 7.5,
      "low": 6.71,
      "close": 7.1,
      "volume": 69,
      "vwap": 7.2116,
      "timestamp": "2025-03-13T16:35:00+00:00"
    },
    {
      "open": 6.9,
      "high": 7,
      "low": 6.2,
      "close": 6.4,
      "volume": 128,
      "vwap": 6.6426,
      "timestamp": "2025-03-13T16:36:00+00:00"
    },
    {
      "open": 6.6,
      "high": 6.6,
      "low": 5.4,
      "close": 5.4,
      "volume": 146,
      "vwap": 5.7542,
      "timestamp": "2025-03-13T16:37:00+00:00"
    },
    {
      "open": 5.57,
      "high": 5.7,
      "low": 5.3,
      "close": 5.6,
      "volume": 31,
      "vwap": 5.4974,
      "timestamp": "2025-03-13T16:38:00+00:00"
    },
    {
      "open": 5.2,
      "high": 5.4,
      "low": 5,
      "close": 5.1,
      "volume": 85,
      "vwap": 5.1676,
      "timestamp": "2025-03-13T16:39:00+00:00"
    },
    {
      "open": 5.1,
      "high": 5.6,
      "low": 4.95,
      "close": 5.3,
      "volume": 74,
      "vwap": 5.4108,
      "timestamp": "2025-03-13T16:40:00+00:00"
    },
    {
      "open": 5.4,
      "high": 6.2,
      "low": 5.19,
      "close": 6.1,
      "volume": 37,
      "vwap": 5.8508,
      "timestamp": "2025-03-13T16:41:00+00:00"
    },
    {
      "open": 6.1,
      "high": 6.4,
      "low": 6.07,
      "close": 6.1,
      "volume": 38,
      "vwap": 6.2632,
      "timestamp": "2025-03-13T16:42:00+00:00"
    },
    {
      "open": 6.45,
      "high": 6.5,
      "low": 6.1,
      "close": 6.1,
      "volume": 23,
      "vwap": 6.3261,
      "timestamp": "2025-03-13T16:43:00+00:00"
    },
    {
      "open": 6.4,
      "high": 8.1,
      "low": 6.4,
      "close": 7.8,
      "volume": 70,
      "vwap": 7.2551,
      "timestamp": "2025-03-13T16:44:00+00:00"
    },
    {
      "open": 7.9,
      "high": 9.3,
      "low": 7.4,
      "close": 9.2,
      "volume": 106,
      "vwap": 8.3145,
      "timestamp": "2025-03-13T16:45:00+00:00"
    },
    {
      "open": 9.19,
      "high": 10.6,
      "low": 9.19,
      "close": 10.3,
      "volume": 107,
      "vwap": 9.799,
      "timestamp": "2025-03-13T16:46:00+00:00"
    },
    {
      "open": 10.2,
      "high": 13.9,
      "low": 9.8,
      "close": 13.54,
      "volume": 219,
      "vwap": 12.4458,
      "timestamp": "2025-03-13T16:47:00+00:00"
    },
    {
      "open": 13.5,
      "high": 14.3,
      "low": 13,
      "close": 13,
      "volume": 174,
      "vwap": 13.5028,
      "timestamp": "2025-03-13T16:48:00+00:00"
    },
    {
      "open": 12.9,
      "high": 13.5,
      "low": 11.65,
      "close": 11.9,
      "volume": 104,
      "vwap": 12.4801,
      "timestamp": "2025-03-13T16:49:00+00:00"
    },
    {
      "open": 12.1,
      "high": 13,
      "low": 10.2,
      "close": 10.6,
      "volume": 133,
      "vwap": 11.1546,
      "timestamp": "2025-03-13T16:50:00+00:00"
    },
    {
      "open": 10.5,
      "high": 11.5,
      "low": 10.2,
      "close": 11.5,
      "volume": 89,
      "vwap": 11.0887,
      "timestamp": "2025-03-13T16:51:00+00:00"
    },
    {
      "open": 10.7,
      "high": 10.7,
      "low": 8.7,
      "close": 9.9,
      "volume": 110,
      "vwap": 9.9174,
      "timestamp": "2025-03-13T16:52:00+00:00"
    },
    {
      "open": 9.9,
      "high": 10.5,
      "low": 8.6,
      "close": 10.4,
      "volume": 96,
      "vwap": 9.2811,
      "timestamp": "2025-03-13T16:53:00+00:00"
    },
    {
      "open": 10.6,
      "high": 12.1,
      "low": 10.58,
      "close": 11.3,
      "volume": 92,
      "vwap": 11.3416,
      "timestamp": "2025-03-13T16:54:00+00:00"
    },
    {
      "open": 11,
      "high": 12,
      "low": 11,
      "close": 12,
      "volume": 28,
      "vwap": 11.5564,
      "timestamp": "2025-03-13T16:55:00+00:00"
    },
    {
      "open": 12.1,
      "high": 12.5,
      "low": 11.3,
      "close": 11.3,
      "volume": 41,
      "vwap": 11.9049,
      "timestamp": "2025-03-13T16:56:00+00:00"
    },
    {
      "open": 11.6,
      "high": 12.2,
      "low": 11.6,
      "close": 12,
      "volume": 26,
      "vwap": 11.7808,
      "timestamp": "2025-03-13T16:57:00+00:00"
    },
    {
      "open": 11.5,
      "high": 12.3,
      "low": 10.8,
      "close": 11.1,
      "volume": 65,
      "vwap": 11.2792,
      "timestamp": "2025-03-13T16:58:00+00:00"
    },
    {
      "open": 11.1,
      "high": 11.7,
      "low": 9.9,
      "close": 10,
      "volume": 158,
      "vwap": 11.1759,
      "timestamp": "2025-03-13T16:59:00+00:00"
    },
    {
      "open": 9.9,
      "high": 10.7,
      "low": 9.1,
      "close": 10.4,
      "volume": 114,
      "vwap": 9.7431,
      "timestamp": "2025-03-13T17:00:00+00:00"
    },
    {
      "open": 9.5,
      "high": 10.9,
      "low": 9.5,
      "close": 10.9,
      "volume": 63,
      "vwap": 10.5268,
      "timestamp": "2025-03-13T17:01:00+00:00"
    },
    {
      "open": 10.7,
      "high": 10.8,
      "low": 10.07,
      "close": 10.6,
      "volume": 78,
      "vwap": 10.6124,
      "timestamp": "2025-03-13T17:02:00+00:00"
    },
    {
      "open": 10.6,
      "high": 11.2,
      "low": 10.5,
      "close": 10.88,
      "volume": 75,
      "vwap": 10.8133,
      "timestamp": "2025-03-13T17:03:00+00:00"
    },
    {
      "open": 10.7,
      "high": 10.7,
      "low": 8.3,
      "close": 8.6,
      "volume": 91,
      "vwap": 9.0822,
      "timestamp": "2025-03-13T17:04:00+00:00"
    },
    {
      "open": 8.3,
      "high": 9.3,
      "low": 7.5,
      "close": 9.1,
      "volume": 100,
      "vwap": 8.2005,
      "timestamp": "2025-03-13T17:05:00+00:00"
    },
    {
      "open": 9.5,
      "high": 11.5,
      "low": 9.4,
      "close": 11.5,
      "volume": 67,
      "vwap": 10.1933,
      "timestamp": "2025-03-13T17:06:00+00:00"
    },
    {
      "open": 10.9,
      "high": 11.2,
      "low": 10.5,
      "close": 10.8,
      "volume": 31,
      "vwap": 10.7613,
      "timestamp": "2025-03-13T17:07:00+00:00"
    },
    {
      "open": 10.8,
      "high": 10.8,
      "low": 10.4,
      "close": 10.67,
      "volume": 18,
      "vwap": 10.6428,
      "timestamp": "2025-03-13T17:08:00+00:00"
    },
    {
      "open": 10.5,
      "high": 11,
      "low": 9.9,
      "close": 10.8,
      "volume": 58,
      "vwap": 10.41,
      "timestamp": "2025-03-13T17:09:00+00:00"
    },
    {
      "open": 10.7,
      "high": 11.6,
      "low": 10.7,
      "close": 11.6,
      "volume": 36,
      "vwap": 11.3089,
      "timestamp": "2025-03-13T17:10:00+00:00"
    },
    {
      "open": 11.76,
      "high": 13.7,
      "low": 11.5,
      "close": 13.3,
      "volume": 108,
      "vwap": 12.9851,
      "timestamp": "2025-03-13T17:11:00+00:00"
    },
    {
      "open": 13,
      "high": 13.7,
      "low": 12.6,
      "close": 13.1,
      "volume": 70,
      "vwap": 13.3421,
      "timestamp": "2025-03-13T17:12:00+00:00"
    },
    {
      "open": 13,
      "high": 13.48,
      "low": 12.53,
      "close": 12.79,
      "volume": 90,
      "vwap": 12.8923,
      "timestamp": "2025-03-13T17:13:00+00:00"
    },
    {
      "open": 12.8,
      "high": 13.3,
      "low": 12.3,
      "close": 12.5,
      "volume": 48,
      "vwap": 12.7352,
      "timestamp": "2025-03-13T17:14:00+00:00"
    },
    {
      "open": 12.5,
      "high": 13.9,
      "low": 12.5,
      "close": 13.9,
      "volume": 47,
      "vwap": 12.8062,
      "timestamp": "2025-03-13T17:15:00+00:00"
    },
    {
      "open": 13.5,
      "high": 15.1,
      "low": 13,
      "close": 14.9,
      "volume": 291,
      "vwap": 14.5721,
      "timestamp": "2025-03-13T17:16:00+00:00"
    },
    {
      "open": 14.8,
      "high": 15.6,
      "low": 14.73,
      "close": 15,
      "volume": 112,
      "vwap": 15.1164,
      "timestamp": "2025-03-13T17:17:00+00:00"
    },
    {
      "open": 14.9,
      "high": 17,
      "low": 14.8,
      "close": 16.1,
      "volume": 248,
      "vwap": 15.8616,
      "timestamp": "2025-03-13T17:18:00+00:00"
    },
    {
      "open": 16.4,
      "high": 17.3,
      "low": 16,
      "close": 16.3,
      "volume": 365,
      "vwap": 16.8613,
      "timestamp": "2025-03-13T17:19:00+00:00"
    },
    {
      "open": 16.3,
      "high": 16.52,
      "low": 14.65,
      "close": 14.7,
      "volume": 142,
      "vwap": 15.7308,
      "timestamp": "2025-03-13T17:20:00+00:00"
    },
    {
      "open": 14.7,
      "high": 15.27,
      "low": 14.2,
      "close": 14.5,
      "volume": 118,
      "vwap": 14.5379,
      "timestamp": "2025-03-13T17:21:00+00:00"
    },
    {
      "open": 14.83,
      "high": 15.02,
      "low": 12.3,
      "close": 12.92,
      "volume": 169,
      "vwap": 13.8127,
      "timestamp": "2025-03-13T17:22:00+00:00"
    },
    {
      "open": 13.06,
      "high": 14.5,
      "low": 13.06,
      "close": 14.1,
      "volume": 79,
      "vwap": 13.9548,
      "timestamp": "2025-03-13T17:23:00+00:00"
    },
    {
      "open": 14.35,
      "high": 14.8,
      "low": 14.2,
      "close": 14.38,
      "volume": 41,
      "vwap": 14.45,
      "timestamp": "2025-03-13T17:24:00+00:00"
    },
    {
      "open": 14.52,
      "high": 15.1,
      "low": 13.8,
      "close": 13.96,
      "volume": 52,
      "vwap": 14.5217,
      "timestamp": "2025-03-13T17:25:00+00:00"
    },
    {
      "open": 13.9,
      "high": 15.3,
      "low": 13.7,
      "close": 14.65,
      "volume": 45,
      "vwap": 14.5002,
      "timestamp": "2025-03-13T17:26:00+00:00"
    },
    {
      "open": 15.2,
      "high": 15.2,
      "low": 14.3,
      "close": 14.4,
      "volume": 60,
      "vwap": 14.592,
      "timestamp": "2025-03-13T17:27:00+00:00"
    },
    {
      "open": 13.8,
      "high": 13.8,
      "low": 12.4,
      "close": 12.7,
      "volume": 91,
      "vwap": 13.1322,
      "timestamp": "2025-03-13T17:28:00+00:00"
    },
    {
      "open": 13.25,
      "high": 13.63,
      "low": 13,
      "close": 13,
      "volume": 23,
      "vwap": 13.2622,
      "timestamp": "2025-03-13T17:29:00+00:00"
    },
    {
      "open": 13.5,
      "high": 14.3,
      "low": 12.8,
      "close": 14.3,
      "volume": 146,
      "vwap": 13.5374,
      "timestamp": "2025-03-13T17:30:00+00:00"
    },
    {
      "open": 14.1,
      "high": 15.8,
      "low": 14.1,
      "close": 15.8,
      "volume": 95,
      "vwap": 15.0264,
      "timestamp": "2025-03-13T17:31:00+00:00"
    },
    {
      "open": 15.7,
      "high": 16.8,
      "low": 15.5,
      "close": 16,
      "volume": 132,
      "vwap": 15.8541,
      "timestamp": "2025-03-13T17:32:00+00:00"
    },
    {
      "open": 16.3,
      "high": 16.4,
      "low": 15.1,
      "close": 16.2,
      "volume": 131,
      "vwap": 15.7141,
      "timestamp": "2025-03-13T17:33:00+00:00"
    },
    {
      "open": 16,
      "high": 16.4,
      "low": 15.5,
      "close": 16.4,
      "volume": 60,
      "vwap": 16.1955,
      "timestamp": "2025-03-13T17:34:00+00:00"
    },
    {
      "open": 16.6,
      "high": 17.12,
      "low": 15.78,
      "close": 16,
      "volume": 184,
      "vwap": 16.6887,
      "timestamp": "2025-03-13T17:35:00+00:00"
    },
    {
      "open": 16,
      "high": 17.1,
      "low": 16,
      "close": 16.67,
      "volume": 101,
      "vwap": 16.6537,
      "timestamp": "2025-03-13T17:36:00+00:00"
    },
    {
      "open": 16.2,
      "high": 17.7,
      "low": 15.7,
      "close": 15.7,
      "volume": 55,
      "vwap": 16.6478,
      "timestamp": "2025-03-13T17:37:00+00:00"
    },
    {
      "open": 15.7,
      "high": 17.1,
      "low": 15.4,
      "close": 16.5,
      "volume": 175,
      "vwap": 16.1129,
      "timestamp": "2025-03-13T17:38:00+00:00"
    },
    {
      "open": 16.4,
      "high": 17.7,
      "low": 16.4,
      "close": 17.6,
      "volume": 116,
      "vwap": 17.2012,
      "timestamp": "2025-03-13T17:39:00+00:00"
    },
    {
      "open": 17.2,
      "high": 17.5,
      "low": 15.1,
      "close": 15.2,
      "volume": 205,
      "vwap": 16.2182,
      "timestamp": "2025-03-13T17:40:00+00:00"
    },
    {
      "open": 15,
      "high": 17.6,
      "low": 14.9,
      "close": 17.1,
      "volume": 141,
      "vwap": 16.494,
      "timestamp": "2025-03-13T17:41:00+00:00"
    },
    {
      "open": 17.2,
      "high": 17.48,
      "low": 16.7,
      "close": 16.7,
      "volume": 113,
      "vwap": 17.0358,
      "timestamp": "2025-03-13T17:42:00+00:00"
    },
    {
      "open": 16.5,
      "high": 16.9,
      "low": 16,
      "close": 16.3,
      "volume": 42,
      "vwap": 16.5079,
      "timestamp": "2025-03-13T17:43:00+00:00"
    },
    {
      "open": 16.6,
      "high": 18,
      "low": 16.6,
      "close": 17.45,
      "volume": 179,
      "vwap": 17.4505,
      "timestamp": "2025-03-13T17:44:00+00:00"
    },
    {
      "open": 17.6,
      "high": 17.7,
      "low": 16.88,
      "close": 17.7,
      "volume": 86,
      "vwap": 17.4055,
      "timestamp": "2025-03-13T17:45:00+00:00"
    },
    {
      "open": 17.6,
      "high": 19,
      "low": 17.5,
      "close": 17.8,
      "volume": 104,
      "vwap": 18.1715,
      "timestamp": "2025-03-13T17:46:00+00:00"
    },
    {
      "open": 18,
      "high": 18.52,
      "low": 17.2,
      "close": 17.8,
      "volume": 100,
      "vwap": 17.8822,
      "timestamp": "2025-03-13T17:47:00+00:00"
    },
    {
      "open": 17.3,
      "high": 18.5,
      "low": 17,
      "close": 18.5,
      "volume": 125,
      "vwap": 18.2132,
      "timestamp": "2025-03-13T17:48:00+00:00"
    },
    {
      "open": 18.1,
      "high": 19.1,
      "low": 17.48,
      "close": 17.6,
      "volume": 87,
      "vwap": 18.2331,
      "timestamp": "2025-03-13T17:49:00+00:00"
    },
    {
      "open": 17.8,
      "high": 17.8,
      "low": 14.65,
      "close": 15.1,
      "volume": 61,
      "vwap": 15.8251,
      "timestamp": "2025-03-13T17:50:00+00:00"
    },
    {
      "open": 15.2,
      "high": 16.7,
      "low": 15.2,
      "close": 15.8,
      "volume": 86,
      "vwap": 15.9849,
      "timestamp": "2025-03-13T17:51:00+00:00"
    },
    {
      "open": 15,
      "high": 15.2,
      "low": 13.2,
      "close": 13.4,
      "volume": 124,
      "vwap": 14.0285,
      "timestamp": "2025-03-13T17:52:00+00:00"
    },
    {
      "open": 13.4,
      "high": 14.9,
      "low": 13.4,
      "close": 13.7,
      "volume": 73,
      "vwap": 14.0799,
      "timestamp": "2025-03-13T17:53:00+00:00"
    },
    {
      "open": 14.27,
      "high": 14.6,
      "low": 13.2,
      "close": 13.2,
      "volume": 49,
      "vwap": 13.9839,
      "timestamp": "2025-03-13T17:54:00+00:00"
    },
    {
      "open": 13.8,
      "high": 14.5,
      "low": 13.1,
      "close": 14.4,
      "volume": 72,
      "vwap": 14.0771,
      "timestamp": "2025-03-13T17:55:00+00:00"
    },
    {
      "open": 14.3,
      "high": 15.1,
      "low": 14,
      "close": 14.2,
      "volume": 86,
      "vwap": 14.5598,
      "timestamp": "2025-03-13T17:56:00+00:00"
    },
    {
      "open": 14.2,
      "high": 16.5,
      "low": 14.15,
      "close": 16.5,
      "volume": 37,
      "vwap": 15.6203,
      "timestamp": "2025-03-13T17:57:00+00:00"
    },
    {
      "open": 16.2,
      "high": 17.2,
      "low": 15.7,
      "close": 16.88,
      "volume": 120,
      "vwap": 16.4217,
      "timestamp": "2025-03-13T17:58:00+00:00"
    },
    {
      "open": 17.2,
      "high": 17.4,
      "low": 16.5,
      "close": 16.6,
      "volume": 68,
      "vwap": 16.9581,
      "timestamp": "2025-03-13T17:59:00+00:00"
    },
    {
      "open": 17.1,
      "high": 17.1,
      "low": 14.3,
      "close": 14.4,
      "volume": 91,
      "vwap": 15.6856,
      "timestamp": "2025-03-13T18:00:00+00:00"
    },
    {
      "open": 14.2,
      "high": 14.8,
      "low": 12,
      "close": 12.4,
      "volume": 57,
      "vwap": 13.4105,
      "timestamp": "2025-03-13T18:01:00+00:00"
    },
    {
      "open": 12.2,
      "high": 12.2,
      "low": 9.8,
      "close": 10,
      "volume": 81,
      "vwap": 10.827,
      "timestamp": "2025-03-13T18:02:00+00:00"
    },
    {
      "open": 10.1,
      "high": 11.7,
      "low": 10,
      "close": 10.3,
      "volume": 108,
      "vwap": 10.9553,
      "timestamp": "2025-03-13T18:03:00+00:00"
    },
    {
      "open": 10.5,
      "high": 11.05,
      "low": 10.2,
      "close": 10.3,
      "volume": 159,
      "vwap": 10.5984,
      "timestamp": "2025-03-13T18:04:00+00:00"
    },
    {
      "open": 10.5,
      "high": 11.1,
      "low": 9.4,
      "close": 9.5,
      "volume": 78,
      "vwap": 10.1495,
      "timestamp": "2025-03-13T18:05:00+00:00"
    },
    {
      "open": 9.4,
      "high": 10.17,
      "low": 9.4,
      "close": 10.17,
      "volume": 53,
      "vwap": 9.7081,
      "timestamp": "2025-03-13T18:06:00+00:00"
    },
    {
      "open": 10.1,
      "high": 10.2,
      "low": 7.89,
      "close": 8.2,
      "volume": 117,
      "vwap": 8.7976,
      "timestamp": "2025-03-13T18:07:00+00:00"
    },
    {
      "open": 8.3,
      "high": 8.72,
      "low": 7.4,
      "close": 7.7,
      "volume": 97,
      "vwap": 8.1364,
      "timestamp": "2025-03-13T18:08:00+00:00"
    },
    {
      "open": 8,
      "high": 8.9,
      "low": 8,
      "close": 8.4,
      "volume": 108,
      "vwap": 8.4797,
      "timestamp": "2025-03-13T18:09:00+00:00"
    },
    {
      "open": 8.63,
      "high": 8.8,
      "low": 7.4,
      "close": 7.4,
      "volume": 106,
      "vwap": 8.3181,
      "timestamp": "2025-03-13T18:10:00+00:00"
    },
    {
      "open": 7.72,
      "high": 7.72,
      "low": 7,
      "close": 7.07,
      "volume": 82,
      "vwap": 7.235,
      "timestamp": "2025-03-13T18:11:00+00:00"
    },
    {
      "open": 6.9,
      "high": 7.16,
      "low": 6.5,
      "close": 6.5,
      "volume": 61,
      "vwap": 6.73,
      "timestamp": "2025-03-13T18:12:00+00:00"
    },
    {
      "open": 6.48,
      "high": 6.48,
      "low": 5.3,
      "close": 5.3,
      "volume": 80,
      "vwap": 6.0025,
      "timestamp": "2025-03-13T18:13:00+00:00"
    },
    {
      "open": 5.2,
      "high": 5.62,
      "low": 5,
      "close": 5.52,
      "volume": 199,
      "vwap": 5.2961,
      "timestamp": "2025-03-13T18:14:00+00:00"
    },
    {
      "open": 5.7,
      "high": 6.5,
      "low": 5.6,
      "close": 6.1,
      "volume": 70,
      "vwap": 5.9883,
      "timestamp": "2025-03-13T18:15:00+00:00"
    },
    {
      "open": 6.4,
      "high": 7,
      "low": 6.4,
      "close": 6.5,
      "volume": 132,
      "vwap": 6.7019,
      "timestamp": "2025-03-13T18:16:00+00:00"
    },
    {
      "open": 7.2,
      "high": 7.85,
      "low": 7.1,
      "close": 7.2,
      "volume": 132,
      "vwap": 7.6217,
      "timestamp": "2025-03-13T18:17:00+00:00"
    },
    {
      "open": 7.4,
      "high": 8.1,
      "low": 7.4,
      "close": 7.67,
      "volume": 45,
      "vwap": 7.7398,
      "timestamp": "2025-03-13T18:18:00+00:00"
    },
    {
      "open": 7.7,
      "high": 7.9,
      "low": 6.3,
      "close": 7.1,
      "volume": 111,
      "vwap": 7.009,
      "timestamp": "2025-03-13T18:19:00+00:00"
    },
    {
      "open": 7.6,
      "high": 7.87,
      "low": 6.1,
      "close": 6.1,
      "volume": 101,
      "vwap": 7.2813,
      "timestamp": "2025-03-13T18:20:00+00:00"
    },
    {
      "open": 6,
      "high": 6.9,
      "low": 6,
      "close": 6.3,
      "volume": 96,
      "vwap": 6.3469,
      "timestamp": "2025-03-13T18:21:00+00:00"
    },
    {
      "open": 6.2,
      "high": 6.4,
      "low": 6.15,
      "close": 6.36,
      "volume": 31,
      "vwap": 6.2597,
      "timestamp": "2025-03-13T18:22:00+00:00"
    },
    {
      "open": 6.5,
      "high": 6.61,
      "low": 5.7,
      "close": 5.8,
      "volume": 59,
      "vwap": 6.0368,
      "timestamp": "2025-03-13T18:23:00+00:00"
    },
    {
      "open": 5.87,
      "high": 5.87,
      "low": 5.2,
      "close": 5.8,
      "volume": 63,
      "vwap": 5.4919,
      "timestamp": "2025-03-13T18:24:00+00:00"
    },
    {
      "open": 5.4,
      "high": 5.45,
      "low": 4.62,
      "close": 4.8,
      "volume": 144,
      "vwap": 4.9703,
      "timestamp": "2025-03-13T18:25:00+00:00"
    },
    {
      "open": 5.15,
      "high": 5.18,
      "low": 4.8,
      "close": 5,
      "volume": 147,
      "vwap": 5.0557,
      "timestamp": "2025-03-13T18:26:00+00:00"
    },
    {
      "open": 4.9,
      "high": 5.3,
      "low": 4.54,
      "close": 5.07,
      "volume": 81,
      "vwap": 4.9202,
      "timestamp": "2025-03-13T18:27:00+00:00"
    },
    {
      "open": 5.3,
      "high": 6.2,
      "low": 5.3,
      "close": 5.4,
      "volume": 44,
      "vwap": 5.6175,
      "timestamp": "2025-03-13T18:28:00+00:00"
    },
    {
      "open": 5.4,
      "high": 5.4,
      "low": 4.5,
      "close": 4.5,
      "volume": 23,
      "vwap": 4.7065,
      "timestamp": "2025-03-13T18:29:00+00:00"
    },
    {
      "open": 4.4,
      "high": 5.3,
      "low": 4.4,
      "close": 4.9,
      "volume": 79,
      "vwap": 4.8157,
      "timestamp": "2025-03-13T18:30:00+00:00"
    },
    {
      "open": 4.7,
      "high": 4.7,
      "low": 4.1,
      "close": 4.3,
      "volume": 179,
      "vwap": 4.2788,
      "timestamp": "2025-03-13T18:31:00+00:00"
    },
    {
      "open": 4.11,
      "high": 4.2,
      "low": 3.6,
      "close": 3.6,
      "volume": 81,
      "vwap": 3.8393,
      "timestamp": "2025-03-13T18:32:00+00:00"
    },
    {
      "open": 3.67,
      "high": 3.7,
      "low": 3.2,
      "close": 3.2,
      "volume": 85,
      "vwap": 3.4551,
      "timestamp": "2025-03-13T18:33:00+00:00"
    },
    {
      "open": 3.2,
      "high": 3.9,
      "low": 3,
      "close": 3.9,
      "volume": 89,
      "vwap": 3.2248,
      "timestamp": "2025-03-13T18:34:00+00:00"
    },
    {
      "open": 3.9,
      "high": 3.9,
      "low": 3.5,
      "close": 3.74,
      "volume": 52,
      "vwap": 3.7767,
      "timestamp": "2025-03-13T18:35:00+00:00"
    },
    {
      "open": 3.8,
      "high": 3.8,
      "low": 2.97,
      "close": 3.3,
      "volume": 63,
      "vwap": 3.3371,
      "timestamp": "2025-03-13T18:36:00+00:00"
    },
    {
      "open": 3.37,
      "high": 3.4,
      "low": 2.6,
      "close": 2.6,
      "volume": 45,
      "vwap": 2.9813,
      "timestamp": "2025-03-13T18:37:00+00:00"
    },
    {
      "open": 2.71,
      "high": 2.9,
      "low": 2.7,
      "close": 2.9,
      "volume": 90,
      "vwap": 2.7713,
      "timestamp": "2025-03-13T18:38:00+00:00"
    },
    {
      "open": 2.95,
      "high": 3.1,
      "low": 2.62,
      "close": 2.95,
      "volume": 147,
      "vwap": 2.7859,
      "timestamp": "2025-03-13T18:39:00+00:00"
    },
    {
      "open": 3,
      "high": 3.15,
      "low": 2.7,
      "close": 3,
      "volume": 84,
      "vwap": 2.8845,
      "timestamp": "2025-03-13T18:40:00+00:00"
    },
    {
      "open": 3.1,
      "high": 3.4,
      "low": 2.65,
      "close": 3,
      "volume": 126,
      "vwap": 3.071,
      "timestamp": "2025-03-13T18:41:00+00:00"
    },
    {
      "open": 3.2,
      "high": 3.2,
      "low": 2.42,
      "close": 2.45,
      "volume": 135,
      "vwap": 2.6941,
      "timestamp": "2025-03-13T18:42:00+00:00"
    },
    {
      "open": 2.55,
      "high": 2.65,
      "low": 2.3,
      "close": 2.4,
      "volume": 35,
      "vwap": 2.498,
      "timestamp": "2025-03-13T18:43:00+00:00"
    },
    {
      "open": 2.4,
      "high": 2.45,
      "low": 2.05,
      "close": 2.15,
      "volume": 96,
      "vwap": 2.1914,
      "timestamp": "2025-03-13T18:44:00+00:00"
    },
    {
      "open": 2.17,
      "high": 2.65,
      "low": 2.05,
      "close": 2.55,
      "volume": 268,
      "vwap": 2.3566,
      "timestamp": "2025-03-13T18:45:00+00:00"
    },
    {
      "open": 2.6,
      "high": 2.8,
      "low": 2.1,
      "close": 2.1,
      "volume": 113,
      "vwap": 2.3981,
      "timestamp": "2025-03-13T18:46:00+00:00"
    },
    {
      "open": 2.1,
      "high": 2.21,
      "low": 2,
      "close": 2.2,
      "volume": 115,
      "vwap": 2.0966,
      "timestamp": "2025-03-13T18:47:00+00:00"
    },
    {
      "open": 2.2,
      "high": 2.2,
      "low": 1.85,
      "close": 1.87,
      "volume": 106,
      "vwap": 1.963,
      "timestamp": "2025-03-13T18:48:00+00:00"
    },
    {
      "open": 1.9,
      "high": 2,
      "low": 1.85,
      "close": 1.95,
      "volume": 43,
      "vwap": 1.9256,
      "timestamp": "2025-03-13T18:49:00+00:00"
    },
    {
      "open": 1.95,
      "high": 2.45,
      "low": 1.85,
      "close": 2.2,
      "volume": 220,
      "vwap": 2.1266,
      "timestamp": "2025-03-13T18:50:00+00:00"
    },
    {
      "open": 2.25,
      "high": 2.65,
      "low": 2.25,
      "close": 2.35,
      "volume": 142,
      "vwap": 2.4346,
      "timestamp": "2025-03-13T18:51:00+00:00"
    },
    {
      "open": 2.35,
      "high": 3.3,
      "low": 2.35,
      "close": 3.1,
      "volume": 281,
      "vwap": 3.0145,
      "timestamp": "2025-03-13T18:52:00+00:00"
    },
    {
      "open": 3.01,
      "high": 3.7,
      "low": 2.8,
      "close": 3.5,
      "volume": 206,
      "vwap": 3.1448,
      "timestamp": "2025-03-13T18:53:00+00:00"
    },
    {
      "open": 3.52,
      "high": 3.8,
      "low": 2.5,
      "close": 2.55,
      "volume": 154,
      "vwap": 3.2819,
      "timestamp": "2025-03-13T18:54:00+00:00"
    },
    {
      "open": 2.55,
      "high": 2.55,
      "low": 2.25,
      "close": 2.25,
      "volume": 55,
      "vwap": 2.3935,
      "timestamp": "2025-03-13T18:55:00+00:00"
    },
    {
      "open": 2.26,
      "high": 3,
      "low": 2.25,
      "close": 2.6,
      "volume": 175,
      "vwap": 2.4719,
      "timestamp": "2025-03-13T18:56:00+00:00"
    },
    {
      "open": 2.5,
      "high": 2.97,
      "low": 2.4,
      "close": 2.75,
      "volume": 73,
      "vwap": 2.6974,
      "timestamp": "2025-03-13T18:57:00+00:00"
    },
    {
      "open": 2.6,
      "high": 2.65,
      "low": 1.9,
      "close": 1.9,
      "volume": 75,
      "vwap": 2.4333,
      "timestamp": "2025-03-13T18:58:00+00:00"
    },
    {
      "open": 1.95,
      "high": 2.05,
      "low": 1.8,
      "close": 1.8,
      "volume": 69,
      "vwap": 1.9062,
      "timestamp": "2025-03-13T18:59:00+00:00"
    },
    {
      "open": 1.85,
      "high": 2.06,
      "low": 1.53,
      "close": 1.6,
      "volume": 226,
      "vwap": 1.738,
      "timestamp": "2025-03-13T19:00:00+00:00"
    },
    {
      "open": 1.5,
      "high": 1.55,
      "low": 1.25,
      "close": 1.25,
      "volume": 127,
      "vwap": 1.4487,
      "timestamp": "2025-03-13T19:01:00+00:00"
    },
    {
      "open": 1.27,
      "high": 1.35,
      "low": 1.1,
      "close": 1.15,
      "volume": 241,
      "vwap": 1.1943,
      "timestamp": "2025-03-13T19:02:00+00:00"
    },
    {
      "open": 1.2,
      "high": 1.5,
      "low": 1.15,
      "close": 1.45,
      "volume": 336,
      "vwap": 1.2852,
      "timestamp": "2025-03-13T19:03:00+00:00"
    },
    {
      "open": 1.4,
      "high": 2.24,
      "low": 1.4,
      "close": 2.05,
      "volume": 138,
      "vwap": 1.7828,
      "timestamp": "2025-03-13T19:04:00+00:00"
    },
    {
      "open": 2.1,
      "high": 2.5,
      "low": 2,
      "close": 2.3,
      "volume": 83,
      "vwap": 2.2665,
      "timestamp": "2025-03-13T19:05:00+00:00"
    },
    {
      "open": 2.25,
      "high": 2.8,
      "low": 2.15,
      "close": 2.65,
      "volume": 221,
      "vwap": 2.449,
      "timestamp": "2025-03-13T19:06:00+00:00"
    },
    {
      "open": 2.65,
      "high": 3.3,
      "low": 2.59,
      "close": 3.3,
      "volume": 142,
      "vwap": 2.9085,
      "timestamp": "2025-03-13T19:07:00+00:00"
    },
    {
      "open": 3.4,
      "high": 4.3,
      "low": 2.95,
      "close": 3.2,
      "volume": 316,
      "vwap": 3.5859,
      "timestamp": "2025-03-13T19:08:00+00:00"
    },
    {
      "open": 3.24,
      "high": 3.4,
      "low": 2.65,
      "close": 3.3,
      "volume": 270,
      "vwap": 2.913,
      "timestamp": "2025-03-13T19:09:00+00:00"
    },
    {
      "open": 3.5,
      "high": 3.92,
      "low": 2.85,
      "close": 3,
      "volume": 120,
      "vwap": 3.3868,
      "timestamp": "2025-03-13T19:10:00+00:00"
    },
    {
      "open": 2.9,
      "high": 3.1,
      "low": 2.4,
      "close": 2.4,
      "volume": 134,
      "vwap": 2.703,
      "timestamp": "2025-03-13T19:11:00+00:00"
    },
    {
      "open": 2.45,
      "high": 2.45,
      "low": 2.15,
      "close": 2.45,
      "volume": 108,
      "vwap": 2.3028,
      "timestamp": "2025-03-13T19:12:00+00:00"
    },
    {
      "open": 2.4,
      "high": 2.45,
      "low": 2.1,
      "close": 2.4,
      "volume": 67,
      "vwap": 2.2649,
      "timestamp": "2025-03-13T19:13:00+00:00"
    },
    {
      "open": 2.3,
      "high": 2.5,
      "low": 1.9,
      "close": 2.2,
      "volume": 122,
      "vwap": 2.1519,
      "timestamp": "2025-03-13T19:14:00+00:00"
    },
    {
      "open": 2.15,
      "high": 2.5,
      "low": 1.75,
      "close": 1.9,
      "volume": 146,
      "vwap": 2.1547,
      "timestamp": "2025-03-13T19:15:00+00:00"
    },
    {
      "open": 1.8,
      "high": 1.8,
      "low": 1.45,
      "close": 1.67,
      "volume": 158,
      "vwap": 1.5418,
      "timestamp": "2025-03-13T19:16:00+00:00"
    },
    {
      "open": 1.7,
      "high": 1.9,
      "low": 1.45,
      "close": 1.75,
      "volume": 92,
      "vwap": 1.7127,
      "timestamp": "2025-03-13T19:17:00+00:00"
    },
    {
      "open": 1.67,
      "high": 2.05,
      "low": 1.5,
      "close": 1.97,
      "volume": 103,
      "vwap": 1.7405,
      "timestamp": "2025-03-13T19:18:00+00:00"
    },
    {
      "open": 1.9,
      "high": 2,
      "low": 1.5,
      "close": 1.52,
      "volume": 79,
      "vwap": 1.6975,
      "timestamp": "2025-03-13T19:19:00+00:00"
    },
    {
      "open": 1.63,
      "high": 2.3,
      "low": 1.63,
      "close": 2.12,
      "volume": 164,
      "vwap": 2.0907,
      "timestamp": "2025-03-13T19:20:00+00:00"
    },
    {
      "open": 2.1,
      "high": 2.4,
      "low": 1.85,
      "close": 2.25,
      "volume": 109,
      "vwap": 2.0615,
      "timestamp": "2025-03-13T19:21:00+00:00"
    },
    {
      "open": 2.16,
      "high": 2.16,
      "low": 1.8,
      "close": 1.85,
      "volume": 53,
      "vwap": 1.9738,
      "timestamp": "2025-03-13T19:22:00+00:00"
    },
    {
      "open": 2,
      "high": 2.1,
      "low": 1.75,
      "close": 2,
      "volume": 66,
      "vwap": 1.9703,
      "timestamp": "2025-03-13T19:23:00+00:00"
    },
    {
      "open": 1.9,
      "high": 2.05,
      "low": 1.7,
      "close": 2,
      "volume": 99,
      "vwap": 1.9698,
      "timestamp": "2025-03-13T19:24:00+00:00"
    },
    {
      "open": 2.05,
      "high": 2.85,
      "low": 1.92,
      "close": 2.7,
      "volume": 296,
      "vwap": 2.4428,
      "timestamp": "2025-03-13T19:25:00+00:00"
    },
    {
      "open": 2.65,
      "high": 3.8,
      "low": 2.4,
      "close": 3.8,
      "volume": 275,
      "vwap": 3.1199,
      "timestamp": "2025-03-13T19:26:00+00:00"
    },
    {
      "open": 3.6,
      "high": 4.47,
      "low": 3.5,
      "close": 4.2,
      "volume": 196,
      "vwap": 3.8967,
      "timestamp": "2025-03-13T19:27:00+00:00"
    },
    {
      "open": 4.1,
      "high": 6,
      "low": 3.6,
      "close": 5.6,
      "volume": 346,
      "vwap": 4.792,
      "timestamp": "2025-03-13T19:28:00+00:00"
    },
    {
      "open": 5.7,
      "high": 5.8,
      "low": 3.7,
      "close": 4.2,
      "volume": 285,
      "vwap": 4.501,
      "timestamp": "2025-03-13T19:29:00+00:00"
    },
    {
      "open": 3.7,
      "high": 5.3,
      "low": 3.4,
      "close": 5.3,
      "volume": 183,
      "vwap": 4.1867,
      "timestamp": "2025-03-13T19:30:00+00:00"
    },
    {
      "open": 5.1,
      "high": 5.1,
      "low": 3.2,
      "close": 3.9,
      "volume": 143,
      "vwap": 3.9355,
      "timestamp": "2025-03-13T19:31:00+00:00"
    },
    {
      "open": 3.5,
      "high": 4.5,
      "low": 3.1,
      "close": 3.8,
      "volume": 181,
      "vwap": 3.5591,
      "timestamp": "2025-03-13T19:32:00+00:00"
    },
    {
      "open": 3.6,
      "high": 3.8,
      "low": 2.1,
      "close": 2.25,
      "volume": 165,
      "vwap": 2.6954,
      "timestamp": "2025-03-13T19:33:00+00:00"
    },
    {
      "open": 2.2,
      "high": 2.65,
      "low": 2.1,
      "close": 2.35,
      "volume": 89,
      "vwap": 2.3434,
      "timestamp": "2025-03-13T19:34:00+00:00"
    },
    {
      "open": 2.5,
      "high": 3.8,
      "low": 2.35,
      "close": 3.8,
      "volume": 118,
      "vwap": 2.8915,
      "timestamp": "2025-03-13T19:35:00+00:00"
    },
    {
      "open": 3.7,
      "high": 4.49,
      "low": 3.6,
      "close": 3.8,
      "volume": 365,
      "vwap": 3.9558,
      "timestamp": "2025-03-13T19:36:00+00:00"
    },
    {
      "open": 3.7,
      "high": 4.4,
      "low": 3.57,
      "close": 3.57,
      "volume": 163,
      "vwap": 3.9456,
      "timestamp": "2025-03-13T19:37:00+00:00"
    },
    {
      "open": 3.8,
      "high": 5.8,
      "low": 3.8,
      "close": 5.5,
      "volume": 515,
      "vwap": 5.2262,
      "timestamp": "2025-03-13T19:38:00+00:00"
    },
    {
      "open": 5.5,
      "high": 6.2,
      "low": 5.1,
      "close": 6.2,
      "volume": 437,
      "vwap": 5.6953,
      "timestamp": "2025-03-13T19:39:00+00:00"
    },
    {
      "open": 6.2,
      "high": 6.32,
      "low": 3.1,
      "close": 3.3,
      "volume": 423,
      "vwap": 5.0148,
      "timestamp": "2025-03-13T19:40:00+00:00"
    },
    {
      "open": 3.4,
      "high": 4.7,
      "low": 3.2,
      "close": 3.7,
      "volume": 234,
      "vwap": 3.6693,
      "timestamp": "2025-03-13T19:41:00+00:00"
    },
    {
      "open": 3.5,
      "high": 5.3,
      "low": 3.3,
      "close": 4.6,
      "volume": 163,
      "vwap": 4.6222,
      "timestamp": "2025-03-13T19:42:00+00:00"
    },
    {
      "open": 4.3,
      "high": 5.47,
      "low": 4.06,
      "close": 4.2,
      "volume": 209,
      "vwap": 4.7445,
      "timestamp": "2025-03-13T19:43:00+00:00"
    },
    {
      "open": 4.3,
      "high": 4.3,
      "low": 2.95,
      "close": 3.2,
      "volume": 214,
      "vwap": 3.3842,
      "timestamp": "2025-03-13T19:44:00+00:00"
    },
    {
      "open": 3.11,
      "high": 4.2,
      "low": 3.11,
      "close": 4.2,
      "volume": 263,
      "vwap": 3.6202,
      "timestamp": "2025-03-13T19:45:00+00:00"
    },
    {
      "open": 4.3,
      "high": 4.36,
      "low": 2,
      "close": 2.35,
      "volume": 382,
      "vwap": 3.4529,
      "timestamp": "2025-03-13T19:46:00+00:00"
    },
    {
      "open": 2.3,
      "high": 2.9,
      "low": 2,
      "close": 2.3,
      "volume": 284,
      "vwap": 2.3187,
      "timestamp": "2025-03-13T19:47:00+00:00"
    },
    {
      "open": 2.2,
      "high": 2.65,
      "low": 1.94,
      "close": 2.1,
      "volume": 159,
      "vwap": 2.1753,
      "timestamp": "2025-03-13T19:48:00+00:00"
    },
    {
      "open": 2,
      "high": 2.3,
      "low": 1.65,
      "close": 2.1,
      "volume": 260,
      "vwap": 1.9317,
      "timestamp": "2025-03-13T19:49:00+00:00"
    },
    {
      "open": 2.3,
      "high": 3.7,
      "low": 2.3,
      "close": 3.1,
      "volume": 534,
      "vwap": 3.1828,
      "timestamp": "2025-03-13T19:50:00+00:00"
    },
    {
      "open": 3.1,
      "high": 5.2,
      "low": 3,
      "close": 3.6,
      "volume": 679,
      "vwap": 4.5173,
      "timestamp": "2025-03-13T19:51:00+00:00"
    },
    {
      "open": 3.6,
      "high": 4,
      "low": 1.75,
      "close": 1.85,
      "volume": 465,
      "vwap": 2.3977,
      "timestamp": "2025-03-13T19:52:00+00:00"
    },
    {
      "open": 1.7,
      "high": 2.7,
      "low": 1.2,
      "close": 2.69,
      "volume": 565,
      "vwap": 1.7587,
      "timestamp": "2025-03-13T19:53:00+00:00"
    },
    {
      "open": 2.94,
      "high": 2.95,
      "low": 0.9,
      "close": 1.25,
      "volume": 463,
      "vwap": 1.7486,
      "timestamp": "2025-03-13T19:54:00+00:00"
    },
    {
      "open": 1.25,
      "high": 1.25,
      "low": 0.25,
      "close": 0.5,
      "volume": 1187,
      "vwap": 0.5668,
      "timestamp": "2025-03-13T19:55:00+00:00"
    },
    {
      "open": 0.5,
      "high": 0.55,
      "low": 0.1,
      "close": 0.2,
      "volume": 780,
      "vwap": 0.2807,
      "timestamp": "2025-03-13T19:56:00+00:00"
    },
    {
      "open": 0.25,
      "high": 0.3,
      "low": 0.1,
      "close": 0.2,
      "volume": 358,
      "vwap": 0.2059,
      "timestamp": "2025-03-13T19:57:00+00:00"
    },
    {
      "open": 0.15,
      "high": 0.35,
      "low": 0.05,
      "close": 0.15,
      "volume": 920,
      "vwap": 0.1164,
      "timestamp": "2025-03-13T19:58:00+00:00"
    },
    {
      "open": 0.15,
      "high": 0.17,
      "low": 0.02,
      "close": 0.02,
      "volume": 301,
      "vwap": 0.0511,
      "timestamp": "2025-03-13T19:59:00+00:00"
    }
  ]
}